peewee_migrations/__init__.py
peewee_migrations/cli.py
peewee_migrations/migrator.py
peewee_migrations-0.3.32.dist-info/LICENSE
peewee_migrations-0.3.32.dist-info/METADATA
peewee_migrations-0.3.32.dist-info/WHEEL
peewee_migrations-0.3.32.dist-info/entry_points.txt
peewee_migrations-0.3.32.dist-info/top_level.txt
peewee_migrations-0.3.32.dist-info/RECORD
