Metadata-Version: 2.1
Name: peewee-migrations
Version: 0.3.32
Summary: Migration engine for peewee orm
Home-page: https://github.com/aachurin/peewee_migrations
Author: Andrey Churin
Author-email: aachurin@gmail.com
License: LGPL3
Platform: any
Classifier: Development Status :: 3 - Alpha
Classifier: Intended Audience :: Developers
Classifier: License :: OSI Approved :: BSD License
Classifier: Operating System :: OS Independent
Classifier: Topic :: Internet :: WWW/HTTP :: Dynamic Content
Classifier: Programming Language :: Python :: 3
Classifier: Programming Language :: Python :: 3.5
Classifier: Programming Language :: Python :: 3.6
Classifier: Programming Language :: Python :: 3.7
License-File: LICENSE
Requires-Dist: peewee (>=3.6.4)
Requires-Dist: click (>=7.0)
